mult_64bit_vedic.srcs/sources_1/new/half_adder.v
`timescale 1ns / 1ps
//////////////////////////////////////////////////////////////////////////////////
// Company: 
// Engineer: 
// 
// Create Date: 09.11.2023 22:02:46
// Design Name: 
// Module Name: half_adder
// Project Name: 
// Target Devices: 
// Tool Versions: 
// Description: 
// 
// Dependencies: 
// 
// Revision:
// Revision 0.01 - File Created
// Additional Comments:
// 
//////////////////////////////////////////////////////////////////////////////////


module half_adder(
    input A,
    input B,
    output Sum,
    output Cout
);

    assign Sum = A ^ B;  // XOR operation for Sum
    assign Cout = A & B; // AND operation for Carry

endmodule

testbenches/half_adder_tb.v
`timescale 1ns / 1ps
`include "../rtl/half_adder.v"
//////////////////////////////////////////////////////////////////////////////////
// Company: 
// Engineer: 
// 
// Create Date: 09.11.2023 22:05:18
// Design Name: 
// Module Name: half_adder_tb
// Project Name: 
// Target Devices: 
// Tool Versions: 
// Description: 
// 
// Dependencies: 
// 
// Revision:
// Revision 0.01 - File Created
// Additional Comments:
// 
//////////////////////////////////////////////////////////////////////////////////


module half_adder_tb();
    // input 
    reg A;
    reg B;
    
    // output
    wire Cout;
    wire Sum;
    
    // instantiate UUT
    half_adder uut(A, B, Cout,Sum);
    
    // initial data
    initial
    begin
        $dumpfile("half_adder_tb.vcd");
        $dumpvars(0, half_adder_tb);
        
        A = 0;
        B = 0;
    end
    
    always #4 A = A + 1'b1;
    always #2 B = B + 1'b1;
    
    initial $monitor($time, A, B, Cout, Sum);
    initial #20 $finish;
    
endmodule

testbenches/half_adder_tb.vcd
$date
	Tue Jan  2 18:16:01 2024
$end
$version
	Icarus Verilog
$end
$timescale
	1ps
$end
$scope module half_adder_tb $end
$var wire 1 ! Sum $end
$var wire 1 " Cout $end
$var reg 1 # A $end
$var reg 1 $ B $end
$scope module uut $end
$var wire 1 # A $end
$var wire 1 $ B $end
$var wire 1 ! Cout $end
$var wire 1 " Sum $end
$upscope $end
$upscope $end
$enddefinitions $end
#0
$dumpvars
0$
0#
0"
0!
$end
#2000
1"
1$
#4000
0$
1#
#6000
0"
1!
1$
#8000
0!
0$
0#
#10000
1"
1$
#12000
0$
1#
#14000
0"
1!
1$
#16000
0!
0$
0#
#18000
1"
1$
#20000
0$
1#
